Magical_Cipher_Disk/__init__.py
Magical_Cipher_Disk/cipher.py
Magical_Cipher_Disk/cipher_io.py
Magical_Cipher_Disk/disk.py
Magical_Cipher_Disk/stones_holder.py
Magical_Cipher_Disk/stones/__init__.py
Magical_Cipher_Disk/stones/base.py
Magical_Cipher_Disk/stones/blue.py
Magical_Cipher_Disk/stones/red_green.py
Magical_Cipher_Disk/stones/yellow.py
magical_cipher_disk-2.1.0.dist-info/licenses/LICENSE
magical_cipher_disk-2.1.0.dist-info/METADATA
magical_cipher_disk-2.1.0.dist-info/WHEEL
magical_cipher_disk-2.1.0.dist-info/top_level.txt
magical_cipher_disk-2.1.0.dist-info/RECORD
