Metadata-Version: 2.4
Name: Magical_Cipher_Disk
Version: 2.1.0
Summary: Cifrado César con añadidos de fantasia, permite encriptar y desencriptar mensajes
Author-email: John Frederick Knight Berra / FrederickKnight <infisefir@gmail.com>
License: MIT License
Project-URL: Homepage, https://github.com/FrederickKnight/Magical_Cipher_Disk
Keywords: python,cipher,encrypted,disk,magic,D&D
Classifier: License :: OSI Approved :: MIT License
Classifier: Programming Language :: Python :: 3.12
Requires-Python: >=3.12
License-File: LICENSE
Requires-Dist: pydantic>=2.11.7
Requires-Dist: unidecode==1.3.8
Dynamic: license-file
